semaclust/__init__.py
semaclust/clusterer.py
semaclust-0.2.0.dist-info/licenses/LICENSE
semaclust-0.2.0.dist-info/METADATA
semaclust-0.2.0.dist-info/WHEEL
semaclust-0.2.0.dist-info/entry_points.txt
semaclust-0.2.0.dist-info/top_level.txt
semaclust-0.2.0.dist-info/RECORD
