Metadata-Version: 2.4
Name: semaclust
Version: 0.2.0
Summary: Semantic text clustering using sentence embeddings and agglomerative clustering
Author-email: Mert Cobanov <mertcobanov@gmail.com>
Maintainer-email: Mert Cobanov <mertcobanov@gmail.com>
License-Expression: MIT
Project-URL: Homepage, https://github.com/cobanov/semaclust
Project-URL: Repository, https://github.com/cobanov/semaclust.git
Project-URL: Documentation, https://github.com/cobanov/semaclust#readme
Project-URL: Changelog, https://github.com/cobanov/semaclust/releases
Project-URL: Issues, https://github.com/cobanov/semaclust/issues
Classifier: Development Status :: 4 - Beta
Classifier: Intended Audience :: Science/Research
Classifier: Intended Audience :: Developers
Classifier: Intended Audience :: Education
Classifier: Operating System :: OS Independent
Classifier: Programming Language :: Python :: 3 :: Only
Classifier: Programming Language :: Python :: 3.7
Classifier: Programming Language :: Python :: 3.8
Classifier: Programming Language :: Python :: 3.9
Classifier: Programming Language :: Python :: 3.10
Classifier: Programming Language :: Python :: 3.11
Classifier: Topic :: Scientific/Engineering
Classifier: Topic :: Scientific/Engineering :: Artificial Intelligence
Classifier: Topic :: Text Processing
Classifier: Topic :: Text Processing :: General
Classifier: Topic :: Text Processing :: Linguistic
Classifier: Topic :: Software Development :: Libraries :: Python Modules
Requires-Python: >=3.7
License-File: LICENSE
Requires-Dist: scikit-learn>=1.0
Requires-Dist: sentence-transformers>=2.2
Requires-Dist: numpy>=1.20
Provides-Extra: dev
Requires-Dist: pytest>=6.0; extra == "dev"
Requires-Dist: pytest-cov>=2.0; extra == "dev"
Requires-Dist: black>=21.12b0; extra == "dev"
Requires-Dist: isort>=5.10.0; extra == "dev"
Requires-Dist: mypy>=0.910; extra == "dev"
Requires-Dist: flake8>=4.0.0; extra == "dev"
Requires-Dist: pre-commit>=2.15.0; extra == "dev"
Provides-Extra: docs
Requires-Dist: sphinx>=4.0.0; extra == "docs"
Requires-Dist: sphinx-rtd-theme>=1.0.0; extra == "docs"
Requires-Dist: myst-parser>=0.15.0; extra == "docs"
Dynamic: license-file
